pynxtools_xrd/__init__.py
pynxtools_xrd/mkdocs.py
pynxtools_xrd/reader.py
pynxtools_xrd/xrd.mapping.json
pynxtools_xrd-0.0.7.dist-info/licenses/LICENSE
pynxtools_xrd-0.0.7.dist-info/METADATA
pynxtools_xrd-0.0.7.dist-info/WHEEL
pynxtools_xrd-0.0.7.dist-info/entry_points.txt
pynxtools_xrd-0.0.7.dist-info/top_level.txt
pynxtools_xrd-0.0.7.dist-info/RECORD
