Metadata-Version: 2.4
Name: pynxtools-xrd
Version: 0.0.7
Summary: A plugin for pynxtools to convert XRD into NeXus application definitions.
Author: The NOMAD Authors
License: 
Project-URL: Homepage, https://github.com/FAIRmat-NFDI/pynxtools-xrd
Project-URL: Parent Project, https://github.com/FAIRmat-NFDI
Classifier: Programming Language :: Python :: 3.10
Classifier: Programming Language :: Python :: 3.11
Classifier: Programming Language :: Python :: 3.12
Classifier: Programming Language :: Python :: 3.13
Classifier: License :: OSI Approved :: Apache Software License
Classifier: Operating System :: OS Independent
Requires-Python: >=3.10
License-File: LICENSE
Requires-Dist: pynxtools>=0.12.0
Requires-Dist: xmltodict
Requires-Dist: fairmat-readers-xrd
Provides-Extra: dev
Requires-Dist: mypy; extra == "dev"
Requires-Dist: ruff>=0.12.0; extra == "dev"
Requires-Dist: pytest; extra == "dev"
Requires-Dist: pytest-cov; extra == "dev"
Requires-Dist: pytest-timeout; extra == "dev"
Requires-Dist: structlog; extra == "dev"
Requires-Dist: types-pyyaml; extra == "dev"
Requires-Dist: types-pytz; extra == "dev"
Requires-Dist: types-requests; extra == "dev"
Requires-Dist: uv; extra == "dev"
Requires-Dist: pre-commit; extra == "dev"
Provides-Extra: docs
Requires-Dist: mkdocs; extra == "docs"
Requires-Dist: mkdocs-material; extra == "docs"
Requires-Dist: mkdocs-material-extensions; extra == "docs"
Requires-Dist: mkdocs-macros-plugin; extra == "docs"
Dynamic: license-file
